<annotation>
	<folder></folder>
	<filename>IMG_20221006_161204_Burst10_jpg.rf.30a1423dfa4b54e4cb4105e6fade7d8f.jpg</filename>
	<path>IMG_20221006_161204_Burst10_jpg.rf.30a1423dfa4b54e4cb4105e6fade7d8f.jpg</path>
	<source>
		<database>roboflow.com</database>
	</source>
	<size>
		<width>640</width>
		<height>640</height>
		<depth>3</depth>
	</size>
	<segmented>0</segmented>
	<object>
		<name>Healthy Leaf</name>
		<pose>Unspecified</pose>
		<truncated>0</truncated>
		<difficult>0</difficult>
		<occluded>0</occluded>
		<bndbox>
			<xmin>452</xmin>
			<xmax>628</xmax>
			<ymin>276</ymin>
			<ymax>418</ymax>
		</bndbox>
	</object>
	<object>
		<name>Healthy Leaf</name>
		<pose>Unspecified</pose>
		<truncated>0</truncated>
		<difficult>0</difficult>
		<occluded>0</occluded>
		<bndbox>
			<xmin>310</xmin>
			<xmax>533</xmax>
			<ymin>237</ymin>
			<ymax>278</ymax>
		</bndbox>
	</object>
	<object>
		<name>Healthy Leaf</name>
		<pose>Unspecified</pose>
		<truncated>0</truncated>
		<difficult>0</difficult>
		<occluded>0</occluded>
		<bndbox>
			<xmin>1</xmin>
			<xmax>292</xmax>
			<ymin>257</ymin>
			<ymax>333</ymax>
		</bndbox>
	</object>
	<object>
		<name>Healthy Leaf</name>
		<pose>Unspecified</pose>
		<truncated>0</truncated>
		<difficult>0</difficult>
		<occluded>0</occluded>
		<bndbox>
			<xmin>1</xmin>
			<xmax>243</xmax>
			<ymin>356</ymin>
			<ymax>419</ymax>
		</bndbox>
	</object>
	<object>
		<name>Healthy Leaf</name>
		<pose>Unspecified</pose>
		<truncated>0</truncated>
		<difficult>0</difficult>
		<occluded>0</occluded>
		<bndbox>
			<xmin>95</xmin>
			<xmax>350</xmax>
			<ymin>448</ymin>
			<ymax>534</ymax>
		</bndbox>
	</object>
	<object>
		<name>Healthy Leaf</name>
		<pose>Unspecified</pose>
		<truncated>0</truncated>
		<difficult>0</difficult>
		<occluded>0</occluded>
		<bndbox>
			<xmin>367</xmin>
			<xmax>576</xmax>
			<ymin>447</ymin>
			<ymax>493</ymax>
		</bndbox>
	</object>
	<object>
		<name>Healthy Leaf</name>
		<pose>Unspecified</pose>
		<truncated>0</truncated>
		<difficult>0</difficult>
		<occluded>0</occluded>
		<bndbox>
			<xmin>233</xmin>
			<xmax>298</xmax>
			<ymin>391</ymin>
			<ymax>445</ymax>
		</bndbox>
	</object>
</annotation>
